[
    {
        "link_of_vacancy": "https://www.superjob.ru/vakansii/senior-golang-developer-38409665.html",
        "salary": {
            "currency": "руб.",
            "max_salary": null,
            "min_salary": 200000
        },
        "site_source": "www.superjob.ru",
        "vacancy_name": "Senior Golang developer"
    },
    {
        "link_of_vacancy": "https://www.superjob.ru/vakansii/programmist-go-38158884.html",
        "salary": {
            "currency": "руб.",
            "max_salary": null,
            "min_salary": 250000
        },
        "site_source": "www.superjob.ru",
        "vacancy_name": "Программист GO (Middle Golang developer, разработчик Go)"
    },
    {
        "link_of_vacancy": "https://www.superjob.ru/vakansii/golang-38285801.html",
        "salary": {
            "currency": "руб.",
            "max_salary": null,
            "min_salary": 180000
        },
        "site_source": "www.superjob.ru",
        "vacancy_name": "Golang / GO developer"
    },
    {
        "link_of_vacancy": "https://www.superjob.ru/vakansii/golang-developer-37934091.html",
        "salary": {
            "currency": "руб.",
            "max_salary": 300000,
            "min_salary": null
        },
        "site_source": "www.superjob.ru",
        "vacancy_name": "Golang Developer"
    },
    {
        "link_of_vacancy": "https://www.superjob.ru/vakansii/programmist-golang-38377376.html",
        "salary": {
            "currency": "руб.",
            "max_salary": null,
            "min_salary": 200000
        },
        "site_source": "www.superjob.ru",
        "vacancy_name": "Программист Golang / Senior Golang developer"
    },
    {
        "link_of_vacancy": "https://www.superjob.ru/vakansii/golang-38137497.html",
        "salary": {
            "currency": "руб.",
            "max_salary": 300000,
            "min_salary": null
        },
        "site_source": "www.superjob.ru",
        "vacancy_name": "Golang (Go)-разработчик Senior"
    },
    {
        "link_of_vacancy": "https://www.superjob.ru/vakansii/razrabotchik-php-37857172.html",
        "salary": {
            "currency": "руб.",
            "max_salary": null,
            "min_salary": 140000
        },
        "site_source": "www.superjob.ru",
        "vacancy_name": "Разработчик PHP"
    },
    {
        "link_of_vacancy": "https://www.superjob.ru/vakansii/senior-software-developer-38347038.html",
        "salary": {
            "currency": null,
            "max_salary": null,
            "min_salary": null
        },
        "site_source": "www.superjob.ru",
        "vacancy_name": "Senior Software developer"
    },
    {
        "link_of_vacancy": "https://www.superjob.ru/vakansii/programmist-bd-38026931.html",
        "salary": {
            "currency": null,
            "max_salary": null,
            "min_salary": null
        },
        "site_source": "www.superjob.ru",
        "vacancy_name": "Программист БД (С++)"
    },
    {
        "link_of_vacancy": "https://www.superjob.ru/vakansii/middle-frontend-razrabotchik-38140289.html",
        "salary": {
            "currency": null,
            "max_salary": null,
            "min_salary": null
        },
        "site_source": "www.superjob.ru",
        "vacancy_name": "Middle Frontend разработчик (React / Redux)"
    },
    {
        "link_of_vacancy": "https://www.superjob.ru/vakansii/devops-inzhener-37997945.html",
        "salary": {
            "currency": "руб.",
            "max_salary": 270000,
            "min_salary": null
        },
        "site_source": "www.superjob.ru",
        "vacancy_name": "DevOps-инженер"
    },
    {
        "link_of_vacancy": "https://www.superjob.ru/vakansii/middle-38285779.html",
        "salary": {
            "currency": "руб.",
            "max_salary": null,
            "min_salary": 150000
        },
        "site_source": "www.superjob.ru",
        "vacancy_name": "Middle / Senior Frontend Developer (React)"
    }
]